{"html_attributions": [], "result": {"rating": 3.1, "reviews": [{"author_name": "Jolanda M\u00fcller", "author_url": "https://www.google.com/maps/contrib/103900911007767443013/reviews", "language": "en", "profile_photo_url": "https://lh3.ggpht.com/-IivyQSx436g/AAAAAAAAAAI/AAAAAAAAAAA/F7Xxaufo77U/s128-c0x00000000-cc-rp-mo-ba3/photo.jpg", "rating": 3, "relative_time_description": "4 months ago", "text": "Just a normal train station, not very pretty or particularly clean and the toilets cost money (20p). The staff are happy and friendly. When we went, our train was on time and we found the station fine. We got lost on the way from the station to the bus stop though and missed the bus. That's because the signs to the bus station are misleading. Better ask a member of staff or trust Maps to navigate.", "time": 1560456868}, {"author_name": "Reto Keller", "author_url": "https://www.google.com/maps/contrib/108853911774465978231/reviews", "language": "en", "profile_photo_url": "https://lh6.ggpht.com/-YB95Yl1B4xw/AAAAAAAAAAI/AAAAAAAAAAA/EGJcXFA0OOY/s128-c0x00000000-cc-rp-mo-ba6/photo.jpg", "rating": 4, "relative_time_description": "a year ago", "text": "It was ok. Nothing special. Toilets could be cleaner. Train left punctual.", "time": 1533232026}, {"author_name": "Kai Maberley", "author_url": "https://www.google.com/maps/contrib/108294963231244540671/reviews", "language": "en", "profile_photo_url": "https://lh5.ggpht.com/-QhZ02SCbSp4/AAAAAAAAAAI/AAAAAAAAAAA/ZD5x96r7oTE/s128-c0x00000000-cc-rp-mo/photo.jpg", "rating": 1, "relative_time_description": "a year ago", "text": "Second time I have been delayed In Elgin and missed my change over to Kyle line. Get new trains!!!! Not that expensive", "time": 1531240805}, {"author_name": "Andrew P Kirk", "author_url": "https://www.google.com/maps/contrib/107580914475033606842/reviews", "language": "en", "profile_photo_url": "https://lh5.ggpht.com/-Z4GJzv188g8/AAAAAAAAAAI/AAAAAAAAAAA/sWNpcART6IE/s128-c0x00000000-cc-rp-mo/photo.jpg", "rating": 1, "relative_time_description": "a year ago", "text": "Like inverMESS bus station, notably Stagecoach & particularly MegaBus. Un-helpful. Obstructive. Dirty filthy trains. Notably windows, both inside & out. With rare exception the staff are just typical of inverMESS. Like the Council. Good for little or nothing! The notice boards should also have been left where they were above platform entrances where the sun seldom shone on it when then it was almost invariably clearly visible...now it's about as helpful as staff & management. Not very bright!", "time": 1538449236}, {"author_name": "Cj Habbishow", "author_url": "https://www.google.com/maps/contrib/101180349167663996383/reviews", "language": "en", "profile_photo_url": "https://lh3.ggpht.com/-vSG7XVspMrY/AAAAAAAAAAI/AAAAAAAAAAA/FbfVoKg64Kc/s128-c0x00000000-cc-rp-mo/photo.jpg", "rating": 5, "relative_time_description": "a year ago", "text": "Spot on, fantastically friendly staff, clean trains, staff available to help, marvellous", "time": 1531582903}]}, "status": "OK"}