{"html_attributions": [], "result": {"rating": 2.6, "reviews": [{"author_name": "Steve Richards", "author_url": "https://www.google.com/maps/contrib/111739070640616146969/reviews", "language": "en", "profile_photo_url": "https://lh5.ggpht.com/-avN9qp783Mo/AAAAAAAAAAI/AAAAAAAAAAA/0PY2iQzXDfM/s128-c0x00000000-cc-rp-mo/photo.jpg", "rating": 1, "relative_time_description": "4 months ago", "text": "Horrible little station. Incorrect information displayed on \u2018useful information\u2019 poster at station and no taxi rank apparently!", "time": 1561463378}, {"author_name": "Dave Everard", "author_url": "https://www.google.com/maps/contrib/115091008527131026824/reviews", "language": "en", "profile_photo_url": "https://lh5.ggpht.com/-w4jxyuOknTg/AAAAAAAAAAI/AAAAAAAAAAA/-GAP0cqkKuI/s128-c0x00000000-cc-rp-mo/photo.jpg", "rating": 3, "relative_time_description": "a year ago", "text": "Not a bad station .\nBut area is a bit run down around it.", "time": 1533489575}, {"author_name": "Mark Hylton", "author_url": "https://www.google.com/maps/contrib/112798855349702408328/reviews", "language": "en", "profile_photo_url": "https://lh6.ggpht.com/-cafkCvNC7Ik/AAAAAAAAAAI/AAAAAAAAAAA/MpCcoEw0m28/s128-c0x00000000-cc-rp-mo-ba4/photo.jpg", "rating": 3, "relative_time_description": "a year ago", "text": "Is a nice station I should have more staff on the stations in the daytime light from 9 the morning till 6 in the evening some the stations to get to Clacton-on-Sea they do not know staff on the platforms but they should do", "time": 1514309175}, {"author_name": "a Mesmerised Being", "author_url": "https://www.google.com/maps/contrib/104177012308356064831/reviews", "language": "en", "profile_photo_url": "https://lh6.ggpht.com/-BuowIc2Wsk4/AAAAAAAAAAI/AAAAAAAAAAA/WAHU0C09dg0/s128-c0x00000000-cc-rp-mo-ba5/photo.jpg", "rating": 3, "relative_time_description": "a year ago", "text": "I wish there was a cafe or a water facility machine there. So thirsty, until get to London\ud83d\ude2d", "time": 1533850218}, {"author_name": "Gaijin", "author_url": "https://www.google.com/maps/contrib/109093090202583933945/reviews", "language": "en", "profile_photo_url": "https://lh3.ggpht.com/-HeyTrtXXTeo/AAAAAAAAAAI/AAAAAAAAAAA/W__uwQhFDlQ/s128-c0x00000000-cc-rp-mo-ba7/photo.jpg", "rating": 3, "relative_time_description": "a year ago", "text": "Clean and well maintained.", "time": 1532353834}]}, "status": "OK"}