{"html_attributions": [], "result": {"rating": 3.7, "reviews": [{"author_name": "Russell Green", "author_url": "https://www.google.com/maps/contrib/104119031001476571008/reviews", "language": "en", "profile_photo_url": "https://lh5.ggpht.com/-JXzxoNjqUC8/AAAAAAAAAAI/AAAAAAAAAAA/c_h_Dlp9J2o/s128-c0x00000000-cc-rp-mo-ba3/photo.jpg", "rating": 2, "relative_time_description": "2 years ago", "text": "The electronic sign posts are frequently broken and or not working. Platform 1 is for trains to Leeds. Platform 2 is for Wakefield and outward bound trains from Leeds.  Recommend using electronic ticket machine if catching the 7:33 to leeds to ensure you have a ticket when you arrive in leeds as the ticket point inside leeds station can be very very busy at times.\n\nthe 7:33 train is often packed, leaving standing room only and little to no chance of purchasing a ticket once on the train.", "time": 1497377589}, {"author_name": "Henry Allum", "author_url": "https://www.google.com/maps/contrib/100063272784199445370/reviews", "language": "en", "profile_photo_url": "https://lh5.ggpht.com/-3QudNxThhac/AAAAAAAAAAI/AAAAAAAAAAA/PpZC6vrl1JU/s128-c0x00000000-cc-rp-mo-ba6/photo.jpg", "rating": 5, "relative_time_description": "2 years ago", "text": "A basic railway station on the Hallam Line.", "time": 1502399523}, {"author_name": "Tom Beresford", "author_url": "https://www.google.com/maps/contrib/112379679516308639227/reviews", "profile_photo_url": "https://lh6.ggpht.com/-lzvIRYhkkfY/AAAAAAAAAAI/AAAAAAAAAAA/EQpKe3hs_js/s128-c0x00000000-cc-rp-mo/photo.jpg", "rating": 4, "relative_time_description": "a year ago", "text": "", "time": 1513606989}, {"author_name": "Stul ynKO", "author_url": "https://www.google.com/maps/contrib/116474242848999765457/reviews", "profile_photo_url": "https://lh4.ggpht.com/-NSiiGZV-lDM/AAAAAAAAAAI/AAAAAAAAAAA/QrtOgOzTSVk/s128-c0x00000000-cc-rp-mo/photo.jpg", "rating": 3, "relative_time_description": "a year ago", "text": "", "time": 1515410361}, {"author_name": "oskie boiiofficial", "author_url": "https://www.google.com/maps/contrib/103585171589800590602/reviews", "profile_photo_url": "https://lh4.ggpht.com/-tfZvZNbJMu4/AAAAAAAAAAI/AAAAAAAAAAA/oupN8Ow6Qyk/s128-c0x00000000-cc-rp-mo-ba2/photo.jpg", "rating": 5, "relative_time_description": "2 years ago", "text": "", "time": 1500015157}]}, "status": "OK"}