{"html_attributions": [], "result": {"rating": 3.8, "reviews": [{"author_name": "Adam Gatto", "author_url": "https://www.google.com/maps/contrib/107013147211161984629/reviews", "language": "en", "profile_photo_url": "https://lh4.ggpht.com/-9sf5XooRp24/AAAAAAAAAAI/AAAAAAAAAAA/if6-5nehpHA/s128-c0x00000000-cc-rp-mo-ba5/photo.jpg", "rating": 4, "relative_time_description": "5 months ago", "text": "Good access to Abbey Wood Shopping Park and the cycle lane.\n\nQuite bare bones as others have said but is tidy.", "time": 1557580255}, {"author_name": "Gabriel Schmitt", "author_url": "https://www.google.com/maps/contrib/103420482254468812568/reviews", "language": "en", "profile_photo_url": "https://lh5.ggpht.com/-b3wMEXqu81o/AAAAAAAAAAI/AAAAAAAAAAA/0TBeZs8YtyI/s128-c0x00000000-cc-rp-mo/photo.jpg", "rating": 4, "relative_time_description": "a month ago", "text": "There are no barriers to  insert your ticket but there are people from morning to afternoon that check your ticket!", "time": 1568438596}, {"author_name": "Tom Beresford", "author_url": "https://www.google.com/maps/contrib/112379679516308639227/reviews", "language": "en", "profile_photo_url": "https://lh6.ggpht.com/-lzvIRYhkkfY/AAAAAAAAAAI/AAAAAAAAAAA/EQpKe3hs_js/s128-c0x00000000-cc-rp-mo/photo.jpg", "rating": 2, "relative_time_description": "10 months ago", "text": "Its facilities are only just adequate. Hard station to find too.", "time": 1544125906}, {"author_name": "Ray Ok", "author_url": "https://www.google.com/maps/contrib/105019780214258739434/reviews", "language": "en", "profile_photo_url": "https://lh3.ggpht.com/-Nr8FrbXVBkA/AAAAAAAAAAI/AAAAAAAAAAA/ox5mBig02eM/s128-c0x00000000-cc-rp-mo-ba5/photo.jpg", "rating": 5, "relative_time_description": "a year ago", "text": "A bare bones station but it has good live arrivals info  and a bloke in a ticket office. Good access to the cycle path and also in easy reach of the shopping centre. Platforms have sheltered waiting areas.", "time": 1523903475}, {"author_name": "Cameron Wallace", "author_url": "https://www.google.com/maps/contrib/117546884264029965655/reviews", "language": "en", "profile_photo_url": "https://lh4.ggpht.com/-sqoJPq4sxUU/AAAAAAAAAAI/AAAAAAAAAAA/jWl1-LhAE7Y/s128-c0x00000000-cc-rp-mo-ba4/photo.jpg", "rating": 4, "relative_time_description": "10 months ago", "text": "The most recent upgrades between Bristol Temple Meads and Parkway include the doubling of the lines to 4, allowing more trains to run.\nIt serves trains to and from Cardiff, Gloucester, Great Malvern, Bristol, Weston Super Mare, Weymouth, Taunton and Portsmouth.\nThe 3 original platforms all have access ramps (no steps) but the new platform only has steps, which are narrower than most. The bridge connecting the platforms weaves all over the place and could take some time to move from one side to the other, depending how many people are there.\nOverall, it's a nice relatively tidy station with good service links.", "time": 1543950348}]}, "status": "OK"}