{"html_attributions": [], "result": {"rating": 3.5, "reviews": [{"author_name": "Martyn Maconachie", "author_url": "https://www.google.com/maps/contrib/115732304960191779859/reviews", "language": "en", "profile_photo_url": "https://lh6.ggpht.com/-jVPdJdEErU8/AAAAAAAAAAI/AAAAAAAAAAA/lxB9a6AEPJg/s128-c0x00000000-cc-rp-mo-ba3/photo.jpg", "rating": 5, "relative_time_description": "4 months ago", "text": "A good local station with facilities including a ticket machine, bike rack and waiting shelter.", "time": 1559156263}, {"author_name": "Philip Mear", "author_url": "https://www.google.com/maps/contrib/110859244305878466671/reviews", "language": "en", "profile_photo_url": "https://lh6.ggpht.com/-Uf_spseWdCg/AAAAAAAAAAI/AAAAAAAAAAA/6b2ILXN8zxk/s128-c0x00000000-cc-rp-mo-ba6/photo.jpg", "rating": 5, "relative_time_description": "2 years ago", "text": "This is a convenient station for Whatstandwell and Crich Carr. Crich itself and the National Tramway Museum are more distant, and a fairly strenuous uphill walk. Hourly services to Derby and Nottingham. Bike rack and limited paid for parking available. A small shelter is available in case of rain. Transpeak buses pass by along the parallel A6 towards Buxton and Manchester. There is a bus stop a few minutes walk away.", "time": 1504116729}, {"author_name": "Wilson Family", "author_url": "https://www.google.com/maps/contrib/103877219565717770593/reviews", "profile_photo_url": "https://lh3.ggpht.com/-Y3gNRpplKR8/AAAAAAAAAAI/AAAAAAAAAAA/r7l9Yqpi0go/s128-c0x00000000-cc-rp-mo/photo.jpg", "rating": 1, "relative_time_description": "a year ago", "text": "", "time": 1525241953}, {"author_name": "Tom Beresford", "author_url": "https://www.google.com/maps/contrib/112379679516308639227/reviews", "profile_photo_url": "https://lh6.ggpht.com/-lzvIRYhkkfY/AAAAAAAAAAI/AAAAAAAAAAA/EQpKe3hs_js/s128-c0x00000000-cc-rp-mo/photo.jpg", "rating": 3, "relative_time_description": "11 months ago", "text": "", "time": 1541426141}]}, "status": "OK"}