{"html_attributions": [], "result": {"rating": 4.6, "reviews": [{"author_name": "Vikas Jain", "author_url": "https://www.google.com/maps/contrib/107670874191777362660/reviews", "language": "en", "profile_photo_url": "https://lh4.ggpht.com/-g50e7pxUQnc/AAAAAAAAAAI/AAAAAAAAAAA/pGdoFFujtkQ/s128-c0x00000000-cc-rp-mo-ba5/photo.jpg", "rating": 5, "relative_time_description": "3 months ago", "text": "Very beautiful. Scenic natural beauty. Must visit during loch lomond trip. Very convenient to travel from Glasgow.", "time": 1562016518}, {"author_name": "Tess Carr", "author_url": "https://www.google.com/maps/contrib/109372470177125921647/reviews", "language": "en", "profile_photo_url": "https://lh6.ggpht.com/-SE22EZWENS4/AAAAAAAAAAI/AAAAAAAAAAA/9gmP0D3inoo/s128-c0x00000000-cc-rp-mo-ba4/photo.jpg", "rating": 5, "relative_time_description": "5 months ago", "text": "Lovely family day out", "time": 1558661045}, {"author_name": "Cpt Choggs", "author_url": "https://www.google.com/maps/contrib/110754507597973701509/reviews", "language": "en", "profile_photo_url": "https://lh3.ggpht.com/-BPJpwI4EnUE/AAAAAAAAAAI/AAAAAAAAAAA/MjI7eqcdYL4/s128-c0x00000000-cc-rp-mo-ba5/photo.jpg", "rating": 4, "relative_time_description": "6 months ago", "text": "Nice and small station.", "time": 1554583810}, {"author_name": "Chris Fuery", "author_url": "https://www.google.com/maps/contrib/108561134159328961143/reviews", "language": "en", "profile_photo_url": "https://lh6.ggpht.com/-W3iH0QtVfMA/AAAAAAAAAAI/AAAAAAAAAAA/ai0-tLJJzCU/s128-c0x00000000-cc-rp-mo-ba5/photo.jpg", "rating": 5, "relative_time_description": "a year ago", "text": "A very beautiful place to stay or visit when up in Scotland has lots of pubs and restaurants over looking the loch and boat trips around the loch and a great place to spend time there lovely parks and gardens and very dog friendly area", "time": 1537821177}, {"author_name": "Tom Ward", "author_url": "https://www.google.com/maps/contrib/110470100384567282271/reviews", "language": "en", "profile_photo_url": "https://lh6.ggpht.com/-p4zMJ7ke42c/AAAAAAAAAAI/AAAAAAAAAAA/Xp0pFbqu0QM/s128-c0x00000000-cc-rp-mo-ba3/photo.jpg", "rating": 4, "relative_time_description": "a year ago", "text": "Friendly people some very good eateries and fantastic short and long Cruise's to take in breathtaking scenery.", "time": 1538158441}]}, "status": "OK"}