{"html_attributions": [], "result": {"rating": 5, "reviews": [{"author_name": "Allan MacIver", "author_url": "https://www.google.com/maps/contrib/104297705149152538299/reviews", "language": "en", "profile_photo_url": "https://lh5.ggpht.com/-dHQA-5uPW-c/AAAAAAAAAAI/AAAAAAAAAAA/QDSQ3n0FADg/s128-c0x00000000-cc-rp-mo-ba5/photo.jpg", "rating": 5, "relative_time_description": "a year ago", "text": "The old station house remains and you cannot miss it in its amazingly bright colour. The day I visited the station was clean and tidy. There is even a little blue train made out if old whisky barrels. In the summer I would assume it will have some nice flowers. There are noticeboards to tell you the arrival/departure of the next train. You can go for a good walk here and return in time for the next train calling.", "time": 1522705716}, {"author_name": "Rk B", "author_url": "https://www.google.com/maps/contrib/101276871027763823466/reviews", "profile_photo_url": "https://lh3.ggpht.com/-G_0--zoYJ3I/AAAAAAAAAAI/AAAAAAAAAAA/g8fd1YRDNwg/s128-c0x00000000-cc-rp-mo-ba6/photo.jpg", "rating": 5, "relative_time_description": "2 weeks ago", "text": "", "time": 1570647848}]}, "status": "OK"}