{"html_attributions": [], "result": {"rating": 4.1, "reviews": [{"author_name": "JK Singh", "author_url": "https://www.google.com/maps/contrib/113968717517799558432/reviews", "language": "en", "profile_photo_url": "https://lh6.ggpht.com/-4vOwI156KJY/AAAAAAAAAAI/AAAAAAAAAAA/-xvrKp6l3No/s128-c0x00000000-cc-rp-mo/photo.jpg", "rating": 5, "relative_time_description": "a year ago", "text": "Great Networking location for Businesses and local commuters. I use this service regularly to travel to London and back. Looking forward to more networks and regular trains at Low Moor. \nBrilliant efforts from the local council to use funding to set up the station and secure the London networks.", "time": 1513682729}, {"author_name": "Jonny Spence", "author_url": "https://www.google.com/maps/contrib/117854271002066042500/reviews", "language": "en", "profile_photo_url": "https://lh5.ggpht.com/-M6oxgCNBSvo/AAAAAAAAAAI/AAAAAAAAAAA/2iq5chu80cI/s128-c0x00000000-cc-rp-mo-ba5/photo.jpg", "rating": 4, "relative_time_description": "2 years ago", "text": "Useful small station, new and clean. The small problem is for the majority of routes you have to get a train to Bradford or Halifax to connect. Not too much of a problem as they're frequent, but still a negative that drops that final star off the score.", "time": 1504848830}, {"author_name": "Mr Nellis", "author_url": "https://www.google.com/maps/contrib/112238244204088032480/reviews", "language": "en", "profile_photo_url": "https://lh4.ggpht.com/-eZvnYKCYi10/AAAAAAAAAAI/AAAAAAAAAAA/CLSP9kUkZOU/s128-c0x00000000-cc-rp-mo/photo.jpg", "rating": 4, "relative_time_description": "a year ago", "text": "Fantastic train station just lacks 2 trains per hour and a direct service to Manchester", "time": 1525119384}, {"author_name": "martyn hartlebury", "author_url": "https://www.google.com/maps/contrib/109124219448476655213/reviews", "language": "en", "profile_photo_url": "https://lh5.ggpht.com/-S8bOubb2w78/AAAAAAAAAAI/AAAAAAAAAAA/gtcmjPi1zik/s128-c0x00000000-cc-rp-mo-ba4/photo.jpg", "rating": 3, "relative_time_description": "a year ago", "text": "It's a basic station", "time": 1526908578}, {"author_name": "jayjay2016", "author_url": "https://www.google.com/maps/contrib/109559381659313396787/reviews", "language": "en", "profile_photo_url": "https://lh5.ggpht.com/-dEqcPylTNVM/AAAAAAAAAAI/AAAAAAAAAAA/QpC0y4oeIDo/s128-c0x00000000-cc-rp-mo/photo.jpg", "rating": 5, "relative_time_description": "2 years ago", "text": "Lovely new clean and not very busy station ideal when going on short hops to leeds or bradford or long hops to london.", "time": 1495290268}]}, "status": "OK"}