{"html_attributions": [], "result": {"rating": 4.8, "reviews": [{"author_name": "Stephen Hall", "author_url": "https://www.google.com/maps/contrib/114571736428276900100/reviews", "language": "en", "profile_photo_url": "https://lh3.ggpht.com/-8Gvm0R9z_zA/AAAAAAAAAAI/AAAAAAAAAAA/udifxqtl7mU/s128-c0x00000000-cc-rp-mo-ba5/photo.jpg", "rating": 5, "relative_time_description": "a month ago", "text": "Nice friendly place", "time": 1567870556}, {"author_name": "Tom Beresford", "author_url": "https://www.google.com/maps/contrib/112379679516308639227/reviews", "language": "en", "profile_photo_url": "https://lh6.ggpht.com/-lzvIRYhkkfY/AAAAAAAAAAI/AAAAAAAAAAA/EQpKe3hs_js/s128-c0x00000000-cc-rp-mo/photo.jpg", "rating": 5, "relative_time_description": "7 months ago", "text": "Well decorated and has all the basic facilities", "time": 1553181192}, {"author_name": "John Robertson", "author_url": "https://www.google.com/maps/contrib/111707186816521040862/reviews", "language": "en", "profile_photo_url": "https://lh6.ggpht.com/-x3UdVMu0-e4/AAAAAAAAAAI/AAAAAAAAAAA/nEi3H-fbPgQ/s128-c0x00000000-cc-rp-mo-ba5/photo.jpg", "rating": 4, "relative_time_description": "a year ago", "text": "Busy station on Buxton to Manchester line . The staion had had a few issues with platform difference between train . Most sorted platform decorated with flowers electric  boards tell you times of train also announcer ticket machine on station . At the side is a popular pub come diner. Disabled access trains regular on time set to run every 30 mins from May 2018. Friendly rail staff helpful.", "time": 1524267461}, {"author_name": "Hero Akira", "author_url": "https://www.google.com/maps/contrib/115384811617204968405/reviews", "language": "en", "profile_photo_url": "https://lh3.ggpht.com/-F8AeaaMWdTQ/AAAAAAAAAAI/AAAAAAAAAAA/v16GgjLRU9U/s128-c0x00000000-cc-rp-mo-ba6/photo.jpg", "rating": 5, "relative_time_description": "a year ago", "text": "Good service", "time": 1528382988}]}, "status": "OK"}